{
  "id": "m5ad.4xlarge",
  "vendor_id": "aws",
  "name": "m5ad.4xlarge",
  "vcpus": 16,
  "cpu_cores": 8,
  "cpu_speed": 2.2,
  "cpu_architecture": "X86_64",
  "cpu_manufacturer": "AMD",
  "memory": 65536,
  "gpu_count": 0,
  "gpu_memory": null,
  "gpu_name": null,
  "gpus": [],
  "storage_size": 600,
  "storage_type": "NVME_SSD",
  "storages": [
    {
      "size": 300,
      "storage_type": "nvme ssd"
    },
    {
      "size": 300,
      "storage_type": "nvme ssd"
    }
  ],
  "network_speed": 5.0,
  "billable_unit": "hour",
  "status": "ACTIVE"
}