{
  "vendor_id": "aws",
  "server_id": "m7a.16xlarge",
  "name": "m7a.16xlarge",
  "api_reference": "m7a.16xlarge",
  "display_name": "m7a.16xlarge",
  "description": "General purpose [AMD processors] Gen7 16xlarge",
  "family": "m7a",
  "vcpus": 64,
  "hypervisor": "nitro",
  "cpu_allocation": "DEDICATED",
  "cpu_cores": 64,
  "cpu_speed": 3.7,
  "cpu_architecture": "X86_64",
  "cpu_manufacturer": "AMD",
  "cpu_family": null,
  "cpu_model": null,
  "cpus": [],
  "memory": 262144,
  "gpu_count": 0,
  "gpu_memory_min": null,
  "gpu_memory_total": null,
  "gpu_manufacturer": null,
  "gpu_model": null,
  "gpus": [],
  "storage_size": 0,
  "storage_type": null,
  "storages": [],
  "network_speed": 25.0,
  "inbound_traffic": 0.0,
  "outbound_traffic": 0.0,
  "ipv4": 0,
  "status": "ACTIVE"
}